README.rst
setup.cfg
setup.py
pyacmedns/__init__.py
pyacmedns/exceptions.py
pyacmedns.egg-info/PKG-INFO
pyacmedns.egg-info/SOURCES.txt
pyacmedns.egg-info/dependency_links.txt
pyacmedns.egg-info/requires.txt
pyacmedns.egg-info/top_level.txt