Metadata-Version: 1.1
Name: pyacmedns
Version: 0.4
Summary: Library that implements the acme-dns client communication and persistent account storage on the client host
Home-page: https://github.com/joohoi/pyacmedns
Author: Joona Hoikkala
Author-email: joona@kuori.org
License: MIT
Download-URL: https://github.com/joohoi/pyacmedns/archive/0.4.tar.gz
Keywords: acme tls x509 acmedns letsencrypt
Platform: UNKNOWN
Classifier: Programming Language :: Python
Classifier: Programming Language :: Python :: 2
Classifier: Programming Language :: Python :: 2.7
Classifier: Programming Language :: Python :: 3
Classifier: Programming Language :: Python :: 3.4
Classifier: Programming Language :: Python :: 3.5
Classifier: Programming Language :: Python :: 3.6
Classifier: Intended Audience :: Developers
Classifier: Intended Audience :: System Administrators
Classifier: License :: OSI Approved :: MIT License
